deepsparse/analytics.py
deepsparse/log.py
deepsparse/analyze.py
deepsparse/version.py
deepsparse/subgraph_execute.py
deepsparse/__init__.py
deepsparse/arch.bin
deepsparse/pipeline_config.py
deepsparse/generated_version.py
deepsparse/debug_analysis.py
deepsparse/engine.py
deepsparse/lib.py
deepsparse/pipeline.py
deepsparse/license.py
deepsparse/cpu.py
deepsparse/tasks.py
deepsparse/image_classification/constants.py
deepsparse/image_classification/__init__.py
deepsparse/image_classification/annotate.py
deepsparse/image_classification/schemas.py
deepsparse/image_classification/validation_script.py
deepsparse/image_classification/preprocess_operator.py
deepsparse/image_classification/pipeline.py
deepsparse/image_classification/postprocess_operator.py
deepsparse/image_classification/utils/__init__.py
deepsparse/image_classification/utils/annotate.py
deepsparse/yolact/__init__.py
deepsparse/yolact/pipelines.py
deepsparse/yolact/annotate.py
deepsparse/yolact/schemas.py
deepsparse/yolact/utils/__init__.py
deepsparse/yolact/utils/annotate.py
deepsparse/yolact/utils/utils.py
deepsparse/yolact/sample_images/__init__.py
deepsparse/operators/operator.py
deepsparse/operators/engine_operator.py
deepsparse/operators/__init__.py
deepsparse/operators/registry.py
deepsparse/utils/imports.py
deepsparse/utils/extractor.py
deepsparse/utils/subgraph.py
deepsparse/utils/time.py
deepsparse/utils/__init__.py
deepsparse/utils/annotate.py
deepsparse/utils/cli_helpers.py
deepsparse/utils/types.py
deepsparse/utils/onnx.py
deepsparse/utils/data.py
deepsparse/utils/timer.py
deepsparse/utils/state.py
deepsparse/loggers/config.py
deepsparse/loggers/logger_manager.py
deepsparse/loggers/constants.py
deepsparse/loggers/root_logger.py
deepsparse/loggers/__init__.py
deepsparse/loggers/utils.py
deepsparse/loggers/logger_factory.py
deepsparse/loggers/async_executor.py
deepsparse/loggers/filters/__init__.py
deepsparse/loggers/filters/pattern.py
deepsparse-1.8.0.dist-info/RECORD
deepsparse-1.8.0.dist-info/WHEEL
deepsparse-1.8.0.dist-info/NOTICE
deepsparse-1.8.0.dist-info/json.license
deepsparse-1.8.0.dist-info/jwt-cpp.license
deepsparse-1.8.0.dist-info/entry_points.txt
deepsparse-1.8.0.dist-info/spookyhash.license
deepsparse-1.8.0.dist-info/protobuf.license
deepsparse-1.8.0.dist-info/xbyak.license
deepsparse-1.8.0.dist-info/top_level.txt
deepsparse-1.8.0.dist-info/fmath.license
deepsparse-1.8.0.dist-info/pybind11.license
deepsparse-1.8.0.dist-info/zlib.license
deepsparse-1.8.0.dist-info/yaml-cpp.license
deepsparse-1.8.0.dist-info/libstdc++.license
deepsparse-1.8.0.dist-info/boost.license
deepsparse-1.8.0.dist-info/LICENSE
deepsparse-1.8.0.dist-info/onnx.license
deepsparse-1.8.0.dist-info/onnx-runtime.license
deepsparse-1.8.0.dist-info/libbacktrace.license
deepsparse-1.8.0.dist-info/tinyformat.license
deepsparse-1.8.0.dist-info/METADATA
deepsparse-1.8.0.dist-info/hwloc.license
