Metadata-Version: 2.1
Name: deepsparse
Version: 1.8.0
Summary: An inference runtime offering GPU-class performance on CPUs and APIs to integrate ML into your application
Home-page: https://github.com/neuralmagic/deepsparse
Author: Neuralmagic, Inc.
Author-email: support@neuralmagic.com
License: Neural Magic DeepSparse Community License
Keywords: inference,machine learning,x86,x86_64,avx2,avx512,neural network,sparse,inference engine,cpu,runtime,deepsparse,computer vision,object detection,sparsity
Classifier: Development Status :: 5 - Production/Stable
Classifier: Programming Language :: Python :: 3
Classifier: Programming Language :: Python :: 3 :: Only
Classifier: Programming Language :: Python :: 3.8
Classifier: Programming Language :: Python :: 3.9
Classifier: Programming Language :: Python :: 3.10
Classifier: Programming Language :: Python :: 3.11
Classifier: Intended Audience :: Developers
Classifier: Intended Audience :: Education
Classifier: Intended Audience :: Information Technology
Classifier: Intended Audience :: Science/Research
Classifier: License :: Other/Proprietary License
Classifier: Operating System :: POSIX :: Linux
Classifier: Topic :: Scientific/Engineering
Classifier: Topic :: Scientific/Engineering :: Artificial Intelligence
Classifier: Topic :: Scientific/Engineering :: Mathematics
Classifier: Topic :: Software Development
Classifier: Topic :: Software Development :: Libraries :: Python Modules
Requires-Python: >=3.8, <3.12
License-File: NOTICE
License-File: LICENSE
License-File: licenses/boost.license
License-File: licenses/fmath.license
License-File: licenses/hwloc.license
License-File: licenses/json.license
License-File: licenses/jwt-cpp.license
License-File: licenses/libbacktrace.license
License-File: licenses/libstdc++.license
License-File: licenses/onnx-runtime.license
License-File: licenses/onnx.license
License-File: licenses/protobuf.license
License-File: licenses/pybind11.license
License-File: licenses/spookyhash.license
License-File: licenses/tinyformat.license
License-File: licenses/xbyak.license
License-File: licenses/yaml-cpp.license
License-File: licenses/zlib.license
Requires-Dist: sparsezoo ~=1.8.0
Requires-Dist: numpy >=1.16.3
Requires-Dist: onnx <1.15.0,>=1.5.0
Requires-Dist: pydantic ~=2.0
Requires-Dist: requests >=2.0.0
Requires-Dist: tqdm >=4.0.0
Requires-Dist: protobuf >=3.12.2
Requires-Dist: click !=8.0.0,>=7.1.2
Provides-Extra: clip
Requires-Dist: open-clip-torch ==2.20.0 ; extra == 'clip'
Requires-Dist: transformers <4.40 ; extra == 'clip'
Provides-Extra: dev
Requires-Dist: beautifulsoup4 >=4.9.3 ; extra == 'dev'
Requires-Dist: black ==22.12.0 ; extra == 'dev'
Requires-Dist: flake8 >=3.8.3 ; extra == 'dev'
Requires-Dist: isort >=5.7.0 ; extra == 'dev'
Requires-Dist: pytest-rerunfailures >=13.0 ; extra == 'dev'
Requires-Dist: ndjson >=0.3.1 ; extra == 'dev'
Requires-Dist: wheel >=0.36.2 ; extra == 'dev'
Requires-Dist: pytest >=6.0.0 ; extra == 'dev'
Requires-Dist: onnxruntime >=1.7.0 ; extra == 'dev'
Requires-Dist: flask >=1.0.0 ; extra == 'dev'
Requires-Dist: flask-cors >=3.0.0 ; extra == 'dev'
Requires-Dist: Pillow >=8.3.2 ; extra == 'dev'
Requires-Dist: openai ; extra == 'dev'
Provides-Extra: docs
Requires-Dist: m2r2 ~=0.2.7 ; extra == 'docs'
Requires-Dist: mistune ==0.8.4 ; extra == 'docs'
Requires-Dist: myst-parser ~=0.14.0 ; extra == 'docs'
Requires-Dist: rinohtype >=0.4.2 ; extra == 'docs'
Requires-Dist: sphinx >=3.4.0 ; extra == 'docs'
Requires-Dist: sphinx-copybutton >=0.3.0 ; extra == 'docs'
Requires-Dist: sphinx-markdown-tables >=0.0.15 ; extra == 'docs'
Requires-Dist: sphinx-multiversion ==0.2.4 ; extra == 'docs'
Requires-Dist: sphinx-rtd-theme ; extra == 'docs'
Provides-Extra: image_classification
Requires-Dist: torchvision >=0.3.0 ; extra == 'image_classification'
Requires-Dist: opencv-python <=4.6.0.66 ; extra == 'image_classification'
Provides-Extra: llm
Requires-Dist: transformers <4.40 ; extra == 'llm'
Requires-Dist: datasets <2.19 ; extra == 'llm'
Requires-Dist: accelerate <0.29 ; extra == 'llm'
Requires-Dist: seqeval ; extra == 'llm'
Requires-Dist: evaluate ; extra == 'llm'
Provides-Extra: onnxruntime
Requires-Dist: onnxruntime >=1.7.0 ; extra == 'onnxruntime'
Provides-Extra: openpifpaf
Requires-Dist: openpifpaf ==0.13.11 ; extra == 'openpifpaf'
Requires-Dist: opencv-python <=4.6.0.66 ; extra == 'openpifpaf'
Requires-Dist: pycocotools >=2.0.6 ; extra == 'openpifpaf'
Requires-Dist: scipy ==1.10.1 ; extra == 'openpifpaf'
Provides-Extra: sentence_transformers
Requires-Dist: optimum-deepsparse ; extra == 'sentence_transformers'
Requires-Dist: torch >=1.7.0 ; extra == 'sentence_transformers'
Provides-Extra: server
Requires-Dist: uvicorn >=0.15.0 ; extra == 'server'
Requires-Dist: fastapi <0.111,>=0.100.0 ; extra == 'server'
Requires-Dist: requests >=2.26.0 ; extra == 'server'
Requires-Dist: python-multipart >=0.0.5 ; extra == 'server'
Requires-Dist: prometheus-client >=0.14.1 ; extra == 'server'
Requires-Dist: psutil >=5.9.4 ; extra == 'server'
Requires-Dist: anyio <4.0.0 ; extra == 'server'
Provides-Extra: torch
Requires-Dist: torch >=1.7.0 ; extra == 'torch'
Provides-Extra: transformers
Requires-Dist: transformers <4.40 ; extra == 'transformers'
Requires-Dist: datasets <2.19 ; extra == 'transformers'
Requires-Dist: accelerate <0.29 ; extra == 'transformers'
Requires-Dist: seqeval ; extra == 'transformers'
Requires-Dist: evaluate ; extra == 'transformers'
Provides-Extra: yolo
Requires-Dist: torchvision >=0.3.0 ; extra == 'yolo'
Requires-Dist: opencv-python <=4.6.0.66 ; extra == 'yolo'
Provides-Extra: yolov5
Requires-Dist: torchvision >=0.3.0 ; extra == 'yolov5'
Requires-Dist: opencv-python <=4.6.0.66 ; extra == 'yolov5'
Provides-Extra: yolov8
Requires-Dist: torchvision >=0.3.0 ; extra == 'yolov8'
Requires-Dist: opencv-python <=4.6.0.66 ; extra == 'yolov8'
Requires-Dist: ultralytics ==8.0.124 ; extra == 'yolov8'
